HISTORY.md
LICENSE.txt
MANIFEST.in
README.md
setup.py
tox.ini
librssreader/__init__.py
librssreader/auth.py
librssreader/inoreader.py
librssreader/inoreaderconfig.py
librssreader/items.py
librssreader/rssreader.py
librssreader/rssreadertools.py
librssreader/theoldreader.py
librssreader/theoldreaderconfig.py
librssreader.egg-info/PKG-INFO
librssreader.egg-info/SOURCES.txt
librssreader.egg-info/dependency_links.txt
librssreader.egg-info/requires.txt
librssreader.egg-info/top_level.txt