Metadata-Version: 1.1
Name: librssreader
Version: 0.0.10
Summary: Library for working with the Google Reader Like API
Home-page: https://github.com/fireinice/librssreader
Author: Zigler Zhang <zigler.zhang@gmail.com>
Author-email: zigler.zhang@gmail.com
License: The MIT License (MIT)
